vindy/__init__.py
vindy/callbacks/__init__.py
vindy/callbacks/pdf_threshold_callback.py
vindy/callbacks/save_coefficients_callback.py
vindy/callbacks/sindy_callback.py
vindy/callbacks/spotify_callback.py
vindy/callbacks/threshold_prune_callback.py
vindy/distributions/__init__.py
vindy/distributions/base_distribution.py
vindy/distributions/gaussian.py
vindy/distributions/laplace.py
vindy/layers/__init__.py
vindy/layers/sindy_layer.py
vindy/layers/vindy_layer.py
vindy/libraries/__init__.py
vindy/libraries/base_library.py
vindy/libraries/exponential_library.py
vindy/libraries/force_library.py
vindy/libraries/fourier_library.py
vindy/libraries/polynomial_library.py
vindy/networks/__init__.py
vindy/networks/autoencoder_sindy.py
vindy/networks/base_model.py
vindy/networks/sindy_network.py
vindy/networks/variational_autoencoder_sindy.py
vindy/utils/__init__.py
vindy/utils/utils.py
vindy-0.1.7.dist-info/LICENSE
vindy-0.1.7.dist-info/METADATA
vindy-0.1.7.dist-info/WHEEL
vindy-0.1.7.dist-info/top_level.txt
vindy-0.1.7.dist-info/RECORD
