Metadata-Version: 2.1
Name: vindy
Version: 0.1.7
Summary: AESINDy is a Python package for automated system identification of low-dimensional systems combining autoencoders and SINDy.
Author-email: Jonas Kneifl <jonas.kneifl@itm.uni-stuttgart.com>, Paolo Conti <paolo.conti@polimi.it>
Project-URL: Homepage, https://github.com/jkneifl/VENI-VINDy-VICI
Project-URL: Issues, https://github.com/jkneifl/VENI-VINDy-VICIissues
Keywords: model order reduction,system identification,surrogate modeling,reduced order models,variational,uncertainty quantification,generative modeling
Classifier: Programming Language :: Python :: 3
Classifier: License :: OSI Approved :: MIT License
Classifier: Operating System :: OS Independent
Requires-Python: >=3.8
License-File: LICENSE
Requires-Dist: matplotlib >=3.7
Requires-Dist: numpy >=1.21.4
Requires-Dist: scikit-learn >=1.2
Requires-Dist: scipy >=1.10
Requires-Dist: sympy >=1.12
Requires-Dist: pysindy >=1.7
Requires-Dist: tensorflow >=2.15
Requires-Dist: tensorflow-probability >=0.24
Requires-Dist: tensorflow-model-optimization >=0.7
Requires-Dist: tf-keras >=2.16
Provides-Extra: gui
Requires-Dist: inspector3D ; extra == 'gui'
Requires-Dist: imageio ; extra == 'gui'
Provides-Extra: interfaces
